{
  "days": [
    {
      "id": 4,
      "name": "Terça-Feira",
      "subtitle": "Inferiores Completo"
    },
    {
      "id": 5,
      "name": "Quarta-Feira",
      "subtitle": "Biceps-triceps"
    }
  ],
  "workouts": [
    {
      "id": 3,
      "day_id": 4,
      "name": "Cadeira Flexora",
      "plannedSets": 3,
      "plannedReps": 12,
      "youtube": null,
      "currentWeight": null,
      "completed": true,
      "position": 1
    },
    {
      "id": 4,
      "day_id": 4,
      "name": "Cadeira Abdutora",
      "plannedSets": 3,
      "plannedReps": 12,
      "youtube": null,
      "currentWeight": null,
      "completed": false,
      "position": 2
    }
  ],
  "logs": [],
  "_ids": {
    "days": 5,
    "workouts": 4,
    "logs": 2
  }
}